mizan_loss/__init__.py
mizan_loss/core.py
mizan_loss-0.1.0.dist-info/licenses/LICENSE
mizan_loss-0.1.0.dist-info/METADATA
mizan_loss-0.1.0.dist-info/WHEEL
mizan_loss-0.1.0.dist-info/top_level.txt
mizan_loss-0.1.0.dist-info/RECORD
