Metadata-Version: 2.4
Name: mizan-loss
Version: 0.1.0
Summary: Mizan Balance Function: scale-invariant loss & similarity metric
Author: Ahsan Shaokat
License: MIT
License-File: LICENSE
Requires-Dist: torch
Dynamic: author
Dynamic: license
Dynamic: license-file
Dynamic: requires-dist
Dynamic: summary
